{
    "version": "5.6.0",
    "flags": {},
    "shapes": [
        {
            "label": "path",
            "points": [
                [
                    115.0,
                    109.0
                ],
                [
                    103.0,
                    121.0
                ],
                [
                    67.0,
                    164.0
                ],
                [
                    68.0,
                    180.0
                ],
                [
                    103.0,
                    229.0
                ],
                [
                    110.0,
                    236.0
                ],
                [
                    173.0,
                    267.0
                ],
                [
                    216.0,
                    285.0
                ],
                [
                    227.0,
                    291.0
                ],
                [
                    240.0,
                    291.0
                ],
                [
                    247.0,
                    285.0
                ],
                [
                    248.0,
                    271.0
                ],
                [
                    242.0,
                    264.0
                ],
                [
                    184.0,
                    239.0
                ],
                [
                    131.0,
                    213.0
                ],
                [
                    125.0,
                    208.0
                ],
                [
                    102.0,
                    176.0
                ],
                [
                    102.0,
                    169.0
                ],
                [
                    118.0,
                    150.0
                ],
                [
                    125.0,
                    144.0
                ],
                [
                    130.0,
                    146.0
                ],
                [
                    172.0,
                    180.0
                ],
                [
                    182.0,
                    180.0
                ],
                [
                    186.0,
                    178.0
                ],
                [
                    191.0,
                    172.0
                ],
                [
                    192.0,
                    161.0
                ],
                [
                    188.0,
                    155.0
                ],
                [
                    131.0,
                    109.0
                ]
            ],
            "group_id": null,
            "description": "",
            "shape_type": "polygon",
            "flags": {},
            "mask": null
        }
    ],
    "imagePath": "../images/1754342352.png",
    "imageData": null,
    "imageHeight": 362,
    "imageWidth": 281
}