{
    "version": "5.6.0",
    "flags": {},
    "shapes": [
        {
            "label": "path",
            "points": [
                [
                    99.0,
                    64.0
                ],
                [
                    83.0,
                    72.0
                ],
                [
                    61.0,
                    96.0
                ],
                [
                    60.0,
                    100.0
                ],
                [
                    62.0,
                    106.0
                ],
                [
                    72.0,
                    127.0
                ],
                [
                    89.0,
                    149.0
                ],
                [
                    88.0,
                    153.0
                ],
                [
                    69.0,
                    181.0
                ],
                [
                    62.0,
                    195.0
                ],
                [
                    61.0,
                    205.0
                ],
                [
                    72.0,
                    229.0
                ],
                [
                    80.0,
                    237.0
                ],
                [
                    100.0,
                    253.0
                ],
                [
                    126.0,
                    269.0
                ],
                [
                    132.0,
                    269.0
                ],
                [
                    135.0,
                    266.0
                ],
                [
                    135.0,
                    259.0
                ],
                [
                    126.0,
                    252.0
                ],
                [
                    107.0,
                    241.0
                ],
                [
                    92.0,
                    229.0
                ],
                [
                    84.0,
                    221.0
                ],
                [
                    76.0,
                    204.0
                ],
                [
                    76.0,
                    200.0
                ],
                [
                    82.0,
                    187.0
                ],
                [
                    105.0,
                    153.0
                ],
                [
                    105.0,
                    146.0
                ],
                [
                    85.0,
                    121.0
                ],
                [
                    77.0,
                    104.0
                ],
                [
                    78.0,
                    97.0
                ],
                [
                    93.0,
                    82.0
                ],
                [
                    112.0,
                    74.0
                ],
                [
                    117.0,
                    76.0
                ],
                [
                    134.0,
                    90.0
                ],
                [
                    155.0,
                    111.0
                ],
                [
                    181.0,
                    125.0
                ],
                [
                    188.0,
                    124.0
                ],
                [
                    203.0,
                    109.0
                ],
                [
                    207.0,
                    108.0
                ],
                [
                    231.0,
                    125.0
                ],
                [
                    254.0,
                    135.0
                ],
                [
                    259.0,
                    133.0
                ],
                [
                    278.0,
                    112.0
                ],
                [
                    284.0,
                    108.0
                ],
                [
                    294.0,
                    105.0
                ],
                [
                    306.0,
                    99.0
                ],
                [
                    321.0,
                    84.0
                ],
                [
                    327.0,
                    85.0
                ],
                [
                    341.0,
                    95.0
                ],
                [
                    347.0,
                    95.0
                ],
                [
                    365.0,
                    85.0
                ],
                [
                    370.0,
                    84.0
                ],
                [
                    383.0,
                    94.0
                ],
                [
                    385.0,
                    97.0
                ],
                [
                    383.0,
                    103.0
                ],
                [
                    374.0,
                    117.0
                ],
                [
                    374.0,
                    124.0
                ],
                [
                    389.0,
                    145.0
                ],
                [
                    389.0,
                    150.0
                ],
                [
                    377.0,
                    169.0
                ],
                [
                    378.0,
                    178.0
                ],
                [
                    386.0,
                    192.0
                ],
                [
                    387.0,
                    197.0
                ],
                [
                    383.0,
                    204.0
                ],
                [
                    372.0,
                    216.0
                ],
                [
                    369.0,
                    222.0
                ],
                [
                    371.0,
                    228.0
                ],
                [
                    388.0,
                    247.0
                ],
                [
                    388.0,
                    252.0
                ],
                [
                    378.0,
                    268.0
                ],
                [
                    349.0,
                    292.0
                ],
                [
                    349.0,
                    298.0
                ],
                [
                    359.0,
                    313.0
                ],
                [
                    362.0,
                    322.0
                ],
                [
                    345.0,
                    341.0
                ],
                [
                    342.0,
                    349.0
                ],
                [
                    349.0,
                    358.0
                ],
                [
                    390.0,
                    396.0
                ],
                [
                    399.0,
                    396.0
                ],
                [
                    400.0,
                    388.0
                ],
                [
                    361.0,
                    349.0
                ],
                [
                    361.0,
                    345.0
                ],
                [
                    375.0,
                    329.0
                ],
                [
                    379.0,
                    322.0
                ],
                [
                    376.0,
                    313.0
                ],
                [
                    367.0,
                    300.0
                ],
                [
                    367.0,
                    295.0
                ],
                [
                    388.0,
                    278.0
                ],
                [
                    405.0,
                    252.0
                ],
                [
                    404.0,
                    244.0
                ],
                [
                    391.0,
                    230.0
                ],
                [
                    387.0,
                    223.0
                ],
                [
                    388.0,
                    219.0
                ],
                [
                    402.0,
                    203.0
                ],
                [
                    403.0,
                    200.0
                ],
                [
                    403.0,
                    195.0
                ],
                [
                    394.0,
                    178.0
                ],
                [
                    393.0,
                    170.0
                ],
                [
                    405.0,
                    151.0
                ],
                [
                    405.0,
                    144.0
                ],
                [
                    390.0,
                    121.0
                ],
                [
                    390.0,
                    118.0
                ],
                [
                    402.0,
                    97.0
                ],
                [
                    402.0,
                    94.0
                ],
                [
                    399.0,
                    89.0
                ],
                [
                    377.0,
                    71.0
                ],
                [
                    371.0,
                    68.0
                ],
                [
                    344.0,
                    80.0
                ],
                [
                    327.0,
                    68.0
                ],
                [
                    320.0,
                    66.0
                ],
                [
                    316.0,
                    68.0
                ],
                [
                    296.0,
                    89.0
                ],
                [
                    275.0,
                    97.0
                ],
                [
                    254.0,
                    118.0
                ],
                [
                    249.0,
                    118.0
                ],
                [
                    231.0,
                    109.0
                ],
                [
                    212.0,
                    94.0
                ],
                [
                    206.0,
                    91.0
                ],
                [
                    202.0,
                    91.0
                ],
                [
                    187.0,
                    106.0
                ],
                [
                    181.0,
                    109.0
                ],
                [
                    163.0,
                    100.0
                ],
                [
                    140.0,
                    77.0
                ],
                [
                    123.0,
                    64.0
                ]
            ],
            "group_id": null,
            "description": "",
            "shape_type": "polygon",
            "flags": {},
            "mask": null
        }
    ],
    "imagePath": "../images/1752485162.png",
    "imageData": null,
    "imageHeight": 460,
    "imageWidth": 466
}