{
    "version": "5.6.0",
    "flags": {},
    "shapes": [
        {
            "label": "path",
            "points": [
                [
                    111.0,
                    36.0
                ],
                [
                    109.0,
                    37.0
                ],
                [
                    106.0,
                    44.0
                ],
                [
                    107.0,
                    66.0
                ],
                [
                    120.0,
                    78.0
                ],
                [
                    128.0,
                    92.0
                ],
                [
                    132.0,
                    92.0
                ],
                [
                    154.0,
                    80.0
                ],
                [
                    158.0,
                    82.0
                ],
                [
                    164.0,
                    88.0
                ],
                [
                    162.0,
                    103.0
                ],
                [
                    175.0,
                    125.0
                ],
                [
                    175.0,
                    128.0
                ],
                [
                    169.0,
                    135.0
                ],
                [
                    166.0,
                    135.0
                ],
                [
                    158.0,
                    130.0
                ],
                [
                    154.0,
                    130.0
                ],
                [
                    145.0,
                    137.0
                ],
                [
                    131.0,
                    153.0
                ],
                [
                    132.0,
                    158.0
                ],
                [
                    150.0,
                    177.0
                ],
                [
                    150.0,
                    180.0
                ],
                [
                    145.0,
                    187.0
                ],
                [
                    144.0,
                    192.0
                ],
                [
                    158.0,
                    203.0
                ],
                [
                    164.0,
                    203.0
                ],
                [
                    176.0,
                    190.0
                ],
                [
                    190.0,
                    179.0
                ],
                [
                    190.0,
                    175.0
                ],
                [
                    185.0,
                    166.0
                ],
                [
                    191.0,
                    159.0
                ],
                [
                    195.0,
                    159.0
                ],
                [
                    204.0,
                    167.0
                ],
                [
                    214.0,
                    173.0
                ],
                [
                    228.0,
                    187.0
                ],
                [
                    232.0,
                    187.0
                ],
                [
                    233.0,
                    182.0
                ],
                [
                    217.0,
                    167.0
                ],
                [
                    211.0,
                    164.0
                ],
                [
                    198.0,
                    153.0
                ],
                [
                    195.0,
                    151.0
                ],
                [
                    190.0,
                    151.0
                ],
                [
                    177.0,
                    165.0
                ],
                [
                    182.0,
                    177.0
                ],
                [
                    160.0,
                    196.0
                ],
                [
                    153.0,
                    190.0
                ],
                [
                    158.0,
                    180.0
                ],
                [
                    158.0,
                    177.0
                ],
                [
                    139.0,
                    154.0
                ],
                [
                    143.0,
                    148.0
                ],
                [
                    154.0,
                    138.0
                ],
                [
                    159.0,
                    138.0
                ],
                [
                    166.0,
                    143.0
                ],
                [
                    170.0,
                    143.0
                ],
                [
                    180.0,
                    133.0
                ],
                [
                    183.0,
                    126.0
                ],
                [
                    177.0,
                    113.0
                ],
                [
                    169.0,
                    101.0
                ],
                [
                    169.0,
                    95.0
                ],
                [
                    171.0,
                    91.0
                ],
                [
                    171.0,
                    86.0
                ],
                [
                    169.0,
                    83.0
                ],
                [
                    158.0,
                    74.0
                ],
                [
                    152.0,
                    73.0
                ],
                [
                    145.0,
                    78.0
                ],
                [
                    132.0,
                    84.0
                ],
                [
                    126.0,
                    75.0
                ],
                [
                    114.0,
                    64.0
                ],
                [
                    111.0,
                    56.0
                ],
                [
                    111.0,
                    50.0
                ],
                [
                    115.0,
                    42.0
                ],
                [
                    114.0,
                    36.0
                ]
            ],
            "group_id": null,
            "description": "",
            "shape_type": "polygon",
            "flags": {},
            "mask": null
        }
    ],
    "imagePath": "../images/1754873560.png",
    "imageData": null,
    "imageHeight": 271,
    "imageWidth": 280
}