{
    "version": "5.6.0",
    "flags": {},
    "shapes": [
        {
            "label": "path",
            "points": [
                [
                    114.0,
                    159.0
                ],
                [
                    109.0,
                    162.0
                ],
                [
                    102.0,
                    170.0
                ],
                [
                    43.0,
                    250.0
                ],
                [
                    40.0,
                    255.0
                ],
                [
                    40.0,
                    276.0
                ],
                [
                    45.0,
                    283.0
                ],
                [
                    60.0,
                    296.0
                ],
                [
                    128.0,
                    363.0
                ],
                [
                    159.0,
                    413.0
                ],
                [
                    159.0,
                    415.0
                ],
                [
                    176.0,
                    440.0
                ],
                [
                    195.0,
                    452.0
                ],
                [
                    274.0,
                    493.0
                ],
                [
                    288.0,
                    493.0
                ],
                [
                    299.0,
                    485.0
                ],
                [
                    303.0,
                    477.0
                ],
                [
                    303.0,
                    465.0
                ],
                [
                    299.0,
                    457.0
                ],
                [
                    287.0,
                    448.0
                ],
                [
                    210.0,
                    408.0
                ],
                [
                    199.0,
                    393.0
                ],
                [
                    176.0,
                    353.0
                ],
                [
                    161.0,
                    331.0
                ],
                [
                    102.0,
                    275.0
                ],
                [
                    94.0,
                    267.0
                ],
                [
                    92.0,
                    262.0
                ],
                [
                    126.0,
                    215.0
                ],
                [
                    130.0,
                    211.0
                ],
                [
                    134.0,
                    211.0
                ],
                [
                    198.0,
                    251.0
                ],
                [
                    268.0,
                    291.0
                ],
                [
                    271.0,
                    294.0
                ],
                [
                    272.0,
                    299.0
                ],
                [
                    266.0,
                    364.0
                ],
                [
                    267.0,
                    378.0
                ],
                [
                    281.0,
                    400.0
                ],
                [
                    303.0,
                    429.0
                ],
                [
                    331.0,
                    470.0
                ],
                [
                    340.0,
                    478.0
                ],
                [
                    345.0,
                    480.0
                ],
                [
                    357.0,
                    480.0
                ],
                [
                    363.0,
                    477.0
                ],
                [
                    369.0,
                    471.0
                ],
                [
                    371.0,
                    468.0
                ],
                [
                    371.0,
                    447.0
                ],
                [
                    330.0,
                    388.0
                ],
                [
                    318.0,
                    373.0
                ],
                [
                    313.0,
                    364.0
                ],
                [
                    315.0,
                    318.0
                ],
                [
                    318.0,
                    297.0
                ],
                [
                    318.0,
                    275.0
                ],
                [
                    315.0,
                    269.0
                ],
                [
                    304.0,
                    259.0
                ],
                [
                    252.0,
                    230.0
                ],
                [
                    239.0,
                    221.0
                ],
                [
                    235.0,
                    220.0
                ],
                [
                    136.0,
                    159.0
                ]
            ],
            "group_id": null,
            "description": "",
            "shape_type": "polygon",
            "flags": {},
            "mask": null
        }
    ],
    "imagePath": "../images/1752387981.png",
    "imageData": null,
    "imageHeight": 502,
    "imageWidth": 421
}