{
    "version": "5.6.0",
    "flags": {},
    "shapes": [
        {
            "label": "path",
            "points": [
                [
                    246.0,
                    38.0
                ],
                [
                    229.0,
                    47.0
                ],
                [
                    200.0,
                    77.0
                ],
                [
                    182.0,
                    93.0
                ],
                [
                    176.0,
                    94.0
                ],
                [
                    163.0,
                    85.0
                ],
                [
                    158.0,
                    84.0
                ],
                [
                    137.0,
                    94.0
                ],
                [
                    105.0,
                    129.0
                ],
                [
                    96.0,
                    146.0
                ],
                [
                    90.0,
                    152.0
                ],
                [
                    73.0,
                    163.0
                ],
                [
                    53.0,
                    183.0
                ],
                [
                    43.0,
                    201.0
                ],
                [
                    43.0,
                    209.0
                ],
                [
                    56.0,
                    220.0
                ],
                [
                    88.0,
                    252.0
                ],
                [
                    107.0,
                    266.0
                ],
                [
                    124.0,
                    275.0
                ],
                [
                    131.0,
                    274.0
                ],
                [
                    144.0,
                    263.0
                ],
                [
                    149.0,
                    263.0
                ],
                [
                    163.0,
                    268.0
                ],
                [
                    167.0,
                    267.0
                ],
                [
                    185.0,
                    244.0
                ],
                [
                    185.0,
                    241.0
                ],
                [
                    180.0,
                    233.0
                ],
                [
                    166.0,
                    217.0
                ],
                [
                    159.0,
                    217.0
                ],
                [
                    146.0,
                    223.0
                ],
                [
                    140.0,
                    223.0
                ],
                [
                    123.0,
                    213.0
                ],
                [
                    117.0,
                    215.0
                ],
                [
                    105.0,
                    233.0
                ],
                [
                    104.0,
                    240.0
                ],
                [
                    107.0,
                    243.0
                ],
                [
                    112.0,
                    242.0
                ],
                [
                    121.0,
                    229.0
                ],
                [
                    124.0,
                    227.0
                ],
                [
                    140.0,
                    235.0
                ],
                [
                    145.0,
                    235.0
                ],
                [
                    161.0,
                    229.0
                ],
                [
                    171.0,
                    240.0
                ],
                [
                    171.0,
                    245.0
                ],
                [
                    163.0,
                    255.0
                ],
                [
                    158.0,
                    255.0
                ],
                [
                    148.0,
                    251.0
                ],
                [
                    141.0,
                    251.0
                ],
                [
                    125.0,
                    263.0
                ],
                [
                    113.0,
                    257.0
                ],
                [
                    94.0,
                    243.0
                ],
                [
                    73.0,
                    221.0
                ],
                [
                    58.0,
                    208.0
                ],
                [
                    56.0,
                    205.0
                ],
                [
                    56.0,
                    201.0
                ],
                [
                    60.0,
                    193.0
                ],
                [
                    64.0,
                    187.0
                ],
                [
                    81.0,
                    170.0
                ],
                [
                    104.0,
                    154.0
                ],
                [
                    114.0,
                    135.0
                ],
                [
                    142.0,
                    104.0
                ],
                [
                    159.0,
                    96.0
                ],
                [
                    173.0,
                    106.0
                ],
                [
                    181.0,
                    108.0
                ],
                [
                    206.0,
                    86.0
                ],
                [
                    235.0,
                    56.0
                ],
                [
                    246.0,
                    50.0
                ],
                [
                    253.0,
                    51.0
                ],
                [
                    264.0,
                    61.0
                ],
                [
                    267.0,
                    74.0
                ],
                [
                    265.0,
                    80.0
                ],
                [
                    229.0,
                    117.0
                ],
                [
                    219.0,
                    123.0
                ],
                [
                    217.0,
                    123.0
                ],
                [
                    214.0,
                    120.0
                ],
                [
                    212.0,
                    113.0
                ],
                [
                    228.0,
                    99.0
                ],
                [
                    229.0,
                    94.0
                ],
                [
                    226.0,
                    91.0
                ],
                [
                    220.0,
                    92.0
                ],
                [
                    201.0,
                    107.0
                ],
                [
                    198.0,
                    111.0
                ],
                [
                    199.0,
                    117.0
                ],
                [
                    208.0,
                    131.0
                ],
                [
                    213.0,
                    136.0
                ],
                [
                    218.0,
                    136.0
                ],
                [
                    222.0,
                    134.0
                ],
                [
                    240.0,
                    122.0
                ],
                [
                    276.0,
                    84.0
                ],
                [
                    276.0,
                    61.0
                ],
                [
                    274.0,
                    55.0
                ],
                [
                    253.0,
                    38.0
                ]
            ],
            "group_id": null,
            "description": "",
            "shape_type": "polygon",
            "flags": {},
            "mask": null
        }
    ],
    "imagePath": "../images/1755467102.png",
    "imageData": null,
    "imageHeight": 320,
    "imageWidth": 310
}