{
    "version": "5.6.0",
    "flags": {},
    "shapes": [
        {
            "label": "path",
            "points": [
                [
                    197.0,
                    30.0
                ],
                [
                    169.0,
                    53.0
                ],
                [
                    131.0,
                    90.0
                ],
                [
                    103.0,
                    128.0
                ],
                [
                    75.0,
                    154.0
                ],
                [
                    73.0,
                    157.0
                ],
                [
                    73.0,
                    164.0
                ],
                [
                    103.0,
                    198.0
                ],
                [
                    111.0,
                    204.0
                ],
                [
                    119.0,
                    202.0
                ],
                [
                    140.0,
                    185.0
                ],
                [
                    142.0,
                    184.0
                ],
                [
                    146.0,
                    186.0
                ],
                [
                    166.0,
                    203.0
                ],
                [
                    187.0,
                    226.0
                ],
                [
                    199.0,
                    238.0
                ],
                [
                    203.0,
                    240.0
                ],
                [
                    208.0,
                    240.0
                ],
                [
                    213.0,
                    236.0
                ],
                [
                    214.0,
                    229.0
                ],
                [
                    212.0,
                    225.0
                ],
                [
                    173.0,
                    185.0
                ],
                [
                    149.0,
                    165.0
                ],
                [
                    146.0,
                    163.0
                ],
                [
                    139.0,
                    163.0
                ],
                [
                    114.0,
                    182.0
                ],
                [
                    99.0,
                    167.0
                ],
                [
                    95.0,
                    161.0
                ],
                [
                    121.0,
                    135.0
                ],
                [
                    143.0,
                    104.0
                ],
                [
                    176.0,
                    71.0
                ],
                [
                    203.0,
                    49.0
                ],
                [
                    213.0,
                    52.0
                ],
                [
                    221.0,
                    56.0
                ],
                [
                    223.0,
                    59.0
                ],
                [
                    204.0,
                    117.0
                ],
                [
                    203.0,
                    126.0
                ],
                [
                    205.0,
                    130.0
                ],
                [
                    219.0,
                    144.0
                ],
                [
                    224.0,
                    152.0
                ],
                [
                    210.0,
                    166.0
                ],
                [
                    205.0,
                    167.0
                ],
                [
                    201.0,
                    165.0
                ],
                [
                    183.0,
                    151.0
                ],
                [
                    175.0,
                    129.0
                ],
                [
                    171.0,
                    121.0
                ],
                [
                    166.0,
                    117.0
                ],
                [
                    160.0,
                    117.0
                ],
                [
                    155.0,
                    121.0
                ],
                [
                    154.0,
                    127.0
                ],
                [
                    157.0,
                    136.0
                ],
                [
                    171.0,
                    166.0
                ],
                [
                    206.0,
                    189.0
                ],
                [
                    213.0,
                    188.0
                ],
                [
                    246.0,
                    156.0
                ],
                [
                    246.0,
                    147.0
                ],
                [
                    244.0,
                    144.0
                ],
                [
                    223.0,
                    122.0
                ],
                [
                    223.0,
                    118.0
                ],
                [
                    225.0,
                    115.0
                ],
                [
                    230.0,
                    95.0
                ],
                [
                    244.0,
                    57.0
                ],
                [
                    244.0,
                    49.0
                ],
                [
                    241.0,
                    45.0
                ],
                [
                    208.0,
                    30.0
                ]
            ],
            "group_id": null,
            "description": "",
            "shape_type": "polygon",
            "flags": {},
            "mask": null
        }
    ],
    "imagePath": "../images/1755079696.png",
    "imageData": null,
    "imageHeight": 276,
    "imageWidth": 277
}