{
    "version": "5.6.0",
    "flags": {},
    "shapes": [
        {
            "label": "path",
            "points": [
                [
                    42.0,
                    124.0
                ],
                [
                    36.0,
                    130.0
                ],
                [
                    37.0,
                    143.0
                ],
                [
                    71.0,
                    172.0
                ],
                [
                    71.0,
                    175.0
                ],
                [
                    67.0,
                    181.0
                ],
                [
                    44.0,
                    210.0
                ],
                [
                    42.0,
                    214.0
                ],
                [
                    42.0,
                    221.0
                ],
                [
                    44.0,
                    225.0
                ],
                [
                    58.0,
                    239.0
                ],
                [
                    84.0,
                    264.0
                ],
                [
                    89.0,
                    267.0
                ],
                [
                    101.0,
                    266.0
                ],
                [
                    106.0,
                    261.0
                ],
                [
                    107.0,
                    253.0
                ],
                [
                    103.0,
                    246.0
                ],
                [
                    73.0,
                    217.0
                ],
                [
                    73.0,
                    215.0
                ],
                [
                    101.0,
                    178.0
                ],
                [
                    103.0,
                    174.0
                ],
                [
                    103.0,
                    167.0
                ],
                [
                    99.0,
                    161.0
                ],
                [
                    91.0,
                    154.0
                ],
                [
                    53.0,
                    124.0
                ]
            ],
            "group_id": null,
            "description": "",
            "shape_type": "polygon",
            "flags": {},
            "mask": null
        }
    ],
    "imagePath": "../images/1754795096.png",
    "imageData": null,
    "imageHeight": 360,
    "imageWidth": 284
}