{
    "version": "5.6.0",
    "flags": {},
    "shapes": [
        {
            "label": "path",
            "points": [
                [
                    197.0,
                    49.0
                ],
                [
                    188.0,
                    55.0
                ],
                [
                    158.0,
                    83.0
                ],
                [
                    155.0,
                    82.0
                ],
                [
                    128.0,
                    58.0
                ],
                [
                    117.0,
                    58.0
                ],
                [
                    75.0,
                    103.0
                ],
                [
                    55.0,
                    134.0
                ],
                [
                    55.0,
                    151.0
                ],
                [
                    82.0,
                    186.0
                ],
                [
                    105.0,
                    210.0
                ],
                [
                    111.0,
                    219.0
                ],
                [
                    75.0,
                    255.0
                ],
                [
                    60.0,
                    290.0
                ],
                [
                    58.0,
                    296.0
                ],
                [
                    58.0,
                    304.0
                ],
                [
                    61.0,
                    310.0
                ],
                [
                    88.0,
                    345.0
                ],
                [
                    105.0,
                    382.0
                ],
                [
                    113.0,
                    390.0
                ],
                [
                    124.0,
                    389.0
                ],
                [
                    162.0,
                    372.0
                ],
                [
                    169.0,
                    365.0
                ],
                [
                    169.0,
                    357.0
                ],
                [
                    151.0,
                    316.0
                ],
                [
                    145.0,
                    311.0
                ],
                [
                    138.0,
                    311.0
                ],
                [
                    132.0,
                    316.0
                ],
                [
                    131.0,
                    324.0
                ],
                [
                    143.0,
                    354.0
                ],
                [
                    140.0,
                    358.0
                ],
                [
                    132.0,
                    362.0
                ],
                [
                    126.0,
                    364.0
                ],
                [
                    122.0,
                    363.0
                ],
                [
                    119.0,
                    360.0
                ],
                [
                    107.0,
                    334.0
                ],
                [
                    82.0,
                    301.0
                ],
                [
                    82.0,
                    296.0
                ],
                [
                    95.0,
                    265.0
                ],
                [
                    138.0,
                    222.0
                ],
                [
                    137.0,
                    213.0
                ],
                [
                    100.0,
                    174.0
                ],
                [
                    78.0,
                    144.0
                ],
                [
                    80.0,
                    136.0
                ],
                [
                    93.0,
                    115.0
                ],
                [
                    110.0,
                    96.0
                ],
                [
                    122.0,
                    84.0
                ],
                [
                    125.0,
                    84.0
                ],
                [
                    151.0,
                    107.0
                ],
                [
                    154.0,
                    109.0
                ],
                [
                    161.0,
                    109.0
                ],
                [
                    177.0,
                    96.0
                ],
                [
                    196.0,
                    77.0
                ],
                [
                    202.0,
                    75.0
                ],
                [
                    227.0,
                    92.0
                ],
                [
                    262.0,
                    130.0
                ],
                [
                    266.0,
                    133.0
                ],
                [
                    273.0,
                    134.0
                ],
                [
                    315.0,
                    103.0
                ],
                [
                    343.0,
                    75.0
                ],
                [
                    351.0,
                    77.0
                ],
                [
                    366.0,
                    87.0
                ],
                [
                    370.0,
                    91.0
                ],
                [
                    370.0,
                    96.0
                ],
                [
                    361.0,
                    121.0
                ],
                [
                    319.0,
                    147.0
                ],
                [
                    282.0,
                    185.0
                ],
                [
                    282.0,
                    197.0
                ],
                [
                    294.0,
                    230.0
                ],
                [
                    297.0,
                    236.0
                ],
                [
                    305.0,
                    241.0
                ],
                [
                    312.0,
                    239.0
                ],
                [
                    317.0,
                    232.0
                ],
                [
                    316.0,
                    224.0
                ],
                [
                    305.0,
                    195.0
                ],
                [
                    306.0,
                    191.0
                ],
                [
                    336.0,
                    161.0
                ],
                [
                    370.0,
                    142.0
                ],
                [
                    379.0,
                    135.0
                ],
                [
                    382.0,
                    130.0
                ],
                [
                    393.0,
                    98.0
                ],
                [
                    393.0,
                    80.0
                ],
                [
                    390.0,
                    77.0
                ],
                [
                    350.0,
                    51.0
                ],
                [
                    340.0,
                    49.0
                ],
                [
                    336.0,
                    51.0
                ],
                [
                    301.0,
                    87.0
                ],
                [
                    279.0,
                    104.0
                ],
                [
                    272.0,
                    107.0
                ],
                [
                    243.0,
                    77.0
                ],
                [
                    202.0,
                    49.0
                ]
            ],
            "group_id": null,
            "description": "",
            "shape_type": "polygon",
            "flags": {},
            "mask": null
        }
    ],
    "imagePath": "../images/1754610877.png",
    "imageData": null,
    "imageHeight": 448,
    "imageWidth": 444
}