{
    "version": "5.6.0",
    "flags": {},
    "shapes": [
        {
            "label": "path",
            "points": [
                [
                    205.0,
                    278.0
                ],
                [
                    189.0,
                    288.0
                ],
                [
                    176.0,
                    299.0
                ],
                [
                    126.0,
                    334.0
                ],
                [
                    111.0,
                    347.0
                ],
                [
                    108.0,
                    353.0
                ],
                [
                    108.0,
                    369.0
                ],
                [
                    111.0,
                    375.0
                ],
                [
                    164.0,
                    455.0
                ],
                [
                    172.0,
                    464.0
                ],
                [
                    197.0,
                    479.0
                ],
                [
                    259.0,
                    512.0
                ],
                [
                    352.0,
                    571.0
                ],
                [
                    368.0,
                    571.0
                ],
                [
                    377.0,
                    566.0
                ],
                [
                    382.0,
                    560.0
                ],
                [
                    385.0,
                    552.0
                ],
                [
                    385.0,
                    546.0
                ],
                [
                    382.0,
                    536.0
                ],
                [
                    378.0,
                    531.0
                ],
                [
                    296.0,
                    477.0
                ],
                [
                    206.0,
                    427.0
                ],
                [
                    200.0,
                    420.0
                ],
                [
                    168.0,
                    371.0
                ],
                [
                    168.0,
                    366.0
                ],
                [
                    173.0,
                    359.0
                ],
                [
                    191.0,
                    349.0
                ],
                [
                    205.0,
                    337.0
                ],
                [
                    210.0,
                    334.0
                ],
                [
                    213.0,
                    334.0
                ],
                [
                    230.0,
                    349.0
                ],
                [
                    285.0,
                    404.0
                ],
                [
                    353.0,
                    482.0
                ],
                [
                    361.0,
                    486.0
                ],
                [
                    372.0,
                    487.0
                ],
                [
                    381.0,
                    484.0
                ],
                [
                    389.0,
                    476.0
                ],
                [
                    391.0,
                    471.0
                ],
                [
                    391.0,
                    453.0
                ],
                [
                    388.0,
                    447.0
                ],
                [
                    323.0,
                    373.0
                ],
                [
                    308.0,
                    358.0
                ],
                [
                    302.0,
                    354.0
                ],
                [
                    257.0,
                    307.0
                ],
                [
                    225.0,
                    278.0
                ]
            ],
            "group_id": null,
            "description": "",
            "shape_type": "polygon",
            "flags": {},
            "mask": null
        }
    ],
    "imagePath": "../images/1753253001.png",
    "imageData": null,
    "imageHeight": 618,
    "imageWidth": 443
}