{
    "version": "5.6.0",
    "flags": {},
    "shapes": [
        {
            "label": "path",
            "points": [
                [
                    309.0,
                    140.0
                ],
                [
                    296.0,
                    158.0
                ],
                [
                    284.0,
                    180.0
                ],
                [
                    283.0,
                    187.0
                ],
                [
                    288.0,
                    205.0
                ],
                [
                    275.0,
                    219.0
                ],
                [
                    274.0,
                    225.0
                ],
                [
                    296.0,
                    248.0
                ],
                [
                    316.0,
                    260.0
                ],
                [
                    354.0,
                    295.0
                ],
                [
                    363.0,
                    308.0
                ],
                [
                    361.0,
                    314.0
                ],
                [
                    357.0,
                    319.0
                ],
                [
                    337.0,
                    337.0
                ],
                [
                    333.0,
                    337.0
                ],
                [
                    317.0,
                    322.0
                ],
                [
                    312.0,
                    322.0
                ],
                [
                    291.0,
                    342.0
                ],
                [
                    275.0,
                    363.0
                ],
                [
                    261.0,
                    376.0
                ],
                [
                    258.0,
                    376.0
                ],
                [
                    252.0,
                    371.0
                ],
                [
                    224.0,
                    345.0
                ],
                [
                    217.0,
                    344.0
                ],
                [
                    200.0,
                    361.0
                ],
                [
                    182.0,
                    376.0
                ],
                [
                    178.0,
                    376.0
                ],
                [
                    165.0,
                    364.0
                ],
                [
                    159.0,
                    364.0
                ],
                [
                    146.0,
                    376.0
                ],
                [
                    143.0,
                    377.0
                ],
                [
                    113.0,
                    359.0
                ],
                [
                    89.0,
                    335.0
                ],
                [
                    86.0,
                    333.0
                ],
                [
                    81.0,
                    334.0
                ],
                [
                    61.0,
                    342.0
                ],
                [
                    59.0,
                    345.0
                ],
                [
                    59.0,
                    352.0
                ],
                [
                    67.0,
                    371.0
                ],
                [
                    84.0,
                    390.0
                ],
                [
                    88.0,
                    390.0
                ],
                [
                    91.0,
                    387.0
                ],
                [
                    91.0,
                    383.0
                ],
                [
                    77.0,
                    365.0
                ],
                [
                    73.0,
                    354.0
                ],
                [
                    75.0,
                    349.0
                ],
                [
                    83.0,
                    346.0
                ],
                [
                    86.0,
                    347.0
                ],
                [
                    106.0,
                    367.0
                ],
                [
                    143.0,
                    390.0
                ],
                [
                    149.0,
                    389.0
                ],
                [
                    160.0,
                    378.0
                ],
                [
                    165.0,
                    379.0
                ],
                [
                    176.0,
                    389.0
                ],
                [
                    182.0,
                    390.0
                ],
                [
                    219.0,
                    358.0
                ],
                [
                    222.0,
                    358.0
                ],
                [
                    256.0,
                    389.0
                ],
                [
                    262.0,
                    390.0
                ],
                [
                    286.0,
                    367.0
                ],
                [
                    303.0,
                    345.0
                ],
                [
                    313.0,
                    336.0
                ],
                [
                    317.0,
                    337.0
                ],
                [
                    332.0,
                    352.0
                ],
                [
                    336.0,
                    352.0
                ],
                [
                    340.0,
                    350.0
                ],
                [
                    363.0,
                    329.0
                ],
                [
                    377.0,
                    311.0
                ],
                [
                    375.0,
                    304.0
                ],
                [
                    357.0,
                    282.0
                ],
                [
                    321.0,
                    250.0
                ],
                [
                    303.0,
                    239.0
                ],
                [
                    289.0,
                    225.0
                ],
                [
                    290.0,
                    220.0
                ],
                [
                    300.0,
                    208.0
                ],
                [
                    300.0,
                    202.0
                ],
                [
                    295.0,
                    185.0
                ],
                [
                    307.0,
                    162.0
                ],
                [
                    318.0,
                    147.0
                ],
                [
                    317.0,
                    140.0
                ]
            ],
            "group_id": null,
            "description": "",
            "shape_type": "polygon",
            "flags": {},
            "mask": null
        },
        {
            "label": "path",
            "points": [
                [
                    301.0,
                    332.0
                ],
                [
                    290.0,
                    343.0
                ],
                [
                    280.0,
                    357.0
                ],
                [
                    260.0,
                    376.0
                ],
                [
                    258.0,
                    376.0
                ],
                [
                    251.0,
                    370.0
                ],
                [
                    223.0,
                    344.0
                ],
                [
                    219.0,
                    343.0
                ],
                [
                    213.0,
                    347.0
                ],
                [
                    182.0,
                    376.0
                ],
                [
                    178.0,
                    376.0
                ],
                [
                    165.0,
                    364.0
                ],
                [
                    159.0,
                    364.0
                ],
                [
                    146.0,
                    376.0
                ],
                [
                    143.0,
                    377.0
                ],
                [
                    112.0,
                    358.0
                ],
                [
                    88.0,
                    334.0
                ],
                [
                    84.0,
                    333.0
                ],
                [
                    61.0,
                    342.0
                ],
                [
                    59.0,
                    345.0
                ],
                [
                    59.0,
                    352.0
                ],
                [
                    69.0,
                    374.0
                ],
                [
                    79.0,
                    386.0
                ],
                [
                    86.0,
                    391.0
                ],
                [
                    91.0,
                    387.0
                ],
                [
                    91.0,
                    383.0
                ],
                [
                    77.0,
                    365.0
                ],
                [
                    73.0,
                    354.0
                ],
                [
                    75.0,
                    349.0
                ],
                [
                    83.0,
                    346.0
                ],
                [
                    107.0,
                    368.0
                ],
                [
                    142.0,
                    390.0
                ],
                [
                    149.0,
                    389.0
                ],
                [
                    161.0,
                    378.0
                ],
                [
                    165.0,
                    379.0
                ],
                [
                    177.0,
                    390.0
                ],
                [
                    182.0,
                    390.0
                ],
                [
                    219.0,
                    358.0
                ],
                [
                    222.0,
                    358.0
                ],
                [
                    256.0,
                    389.0
                ],
                [
                    262.0,
                    390.0
                ],
                [
                    287.0,
                    366.0
                ],
                [
                    298.0,
                    351.0
                ],
                [
                    312.0,
                    337.0
                ],
                [
                    315.0,
                    336.0
                ],
                [
                    318.0,
                    338.0
                ],
                [
                    332.0,
                    352.0
                ],
                [
                    337.0,
                    352.0
                ],
                [
                    355.0,
                    337.0
                ],
                [
                    360.0,
                    332.0
                ],
                [
                    343.0,
                    332.0
                ],
                [
                    337.0,
                    337.0
                ],
                [
                    333.0,
                    337.0
                ],
                [
                    328.0,
                    332.0
                ]
            ],
            "group_id": null,
            "description": "",
            "shape_type": "polygon",
            "flags": {},
            "mask": null
        }
    ],
    "imagePath": "../images/1753450683.png",
    "imageData": null,
    "imageHeight": 454,
    "imageWidth": 448
}